django_react_templatetags/__init__.py
django_react_templatetags/context_processors.py
django_react_templatetags/encoders.py
django_react_templatetags/mixins.py
django_react_templatetags/ssr/__init__.py
django_react_templatetags/ssr/default.py
django_react_templatetags/ssr/hypernova.py
django_react_templatetags/templates/react_print.html
django_react_templatetags/templatetags/__init__.py
django_react_templatetags/templatetags/react.py
django_react_templatetags/tests/__init__.py
django_react_templatetags/tests/mock_response.py
django_react_templatetags/tests/test_filters.py
django_react_templatetags/tests/test_manager.py
django_react_templatetags/tests/test_representation_mixin.py
django_react_templatetags/tests/test_ssr.py
django_react_templatetags/tests/test_ssr_custom_service.py
django_react_templatetags/tests/test_ssr_default_service.py
django_react_templatetags/tests/test_ssr_hypernova_service.py
django_react_templatetags/tests/demosite/__init__.py
django_react_templatetags/tests/demosite/models.py
django_react_templatetags/tests/demosite/settings.py
django_react_templatetags/tests/demosite/urls.py
django_react_templatetags/tests/demosite/views.py
django_react_templatetags-8.0.0.dist-info/LICENSE
django_react_templatetags-8.0.0.dist-info/METADATA
django_react_templatetags-8.0.0.dist-info/WHEEL
django_react_templatetags-8.0.0.dist-info/top_level.txt
django_react_templatetags-8.0.0.dist-info/RECORD
