Metadata-Version: 2.1
Name: django_react_templatetags
Version: 8.0.0
Summary: This django library allows you to add React components into your django templates.
Home-page: https://github.com/frojd/django-react-templatetags
Author: Fröjd
Author-email: martin@marteinn.se
License: MIT
Classifier: Development Status :: 5 - Production/Stable
Classifier: Environment :: Web Environment
Classifier: Intended Audience :: Developers
Classifier: Natural Language :: English
Classifier: Intended Audience :: Developers
Classifier: License :: OSI Approved :: MIT License
Classifier: Programming Language :: Python
Classifier: Programming Language :: Python :: 3
Classifier: Programming Language :: Python :: 3.8
Classifier: Programming Language :: Python :: 3.9
Classifier: Programming Language :: Python :: 3.10
Classifier: Programming Language :: Python :: 3.11
Classifier: Programming Language :: Python :: 3.12
Classifier: Framework :: Django
Classifier: Framework :: Django :: 3.2
Classifier: Framework :: Django :: 4.2
Classifier: Framework :: Django :: 5.0
Classifier: Topic :: Utilities
Classifier: Programming Language :: JavaScript
License-File: LICENSE
Requires-Dist: Django >=3.2
Provides-Extra: hypernova
Requires-Dist: hypernova ; extra == 'hypernova'
Provides-Extra: ssr
Requires-Dist: requests ; extra == 'ssr'
